<?xml version="1.0" encoding="UTF-8"?>
<helpDesk idTickets="10001" idUsuarios="25009" ticketsCerrados="0" ticketsSiendoAtendidos="0" ticketsSinAtender="1"><clientes><cliente email="" fechaAtencion="" id="25009" login="cliente1" nombre="cliente1" password="pass" tipo="4"><ticket calificacion="0" cifrado="false" comentarioCliente="comentario queja 1" comentarioEmpleado="" experto="true" fechaAtencion="" fechaCierre="" fechaCreacion="1242336305938" id="10001" reabierto="false" tipo="1"/></cliente></clientes><empleados><empleado calificacion="0" clave="114" id="25008" incidentes="0" login="Juan1" nombre="Juan" password="j" tipo="3"/><empleado calificacion="0" clave="5" id="25007" incidentes="0" login="Ramirez1" nombre="Ramirez" password="r" tipo="2"/><empleado calificacion="0" clave="87" id="25005" incidentes="0" login="Danilo1" nombre="Danilo" password="d" tipo="2"/><empleado calificacion="0" clave="-119" id="25004" incidentes="0" login="Stucki1" nombre="Stucki" password="s" tipo="2"/><empleado calificacion="0" clave="95" id="25003" incidentes="0" login="Silva1" nombre="Silva" password="s" tipo="3"/><empleado calificacion="0" clave="-77" id="25002" incidentes="0" login="Nicolas1" nombre="Nicolas" password="n" tipo="2"/><empleado calificacion="0" clave="-35" id="25001" incidentes="0" login="Emilio1" nombre="Emilio" password="e" tipo="1"/><empleado calificacion="0" clave="120" id="25006" incidentes="0" login="Diego1" nombre="Diego" password="d" tipo="1"><ticket id="10001"/></empleado></empleados><incidentes/><actividades><actividad nombre="Nueva solicitud (Cliente)" numeroVecesEjecutada="1" promedioTiempo="5"><arcoCon nombre="Asignar ticket(Sistema)"/></actividad><actividad nombre="Cifrar ticket (Sistema)" numeroVecesEjecutada="0" promedioTiempo="0"><arcoCon nombre="Atender ticket (Empleado)"/></actividad><actividad nombre="Asignar ticket(Sistema)" numeroVecesEjecutada="1" promedioTiempo="0"><arcoCon nombre="Atender ticket (Empleado)"/><arcoCon nombre="Cifrar ticket (Sistema)"/></actividad><actividad nombre="Atender ticket (Empleado)" numeroVecesEjecutada="0" promedioTiempo="0"><arcoCon nombre="Cerrar ticket (Empleado)"/></actividad><actividad nombre="Cerrar ticket (Empleado)" numeroVecesEjecutada="0" promedioTiempo="0"><arcoCon nombre="Notificar al cliente (Sistema)"/></actividad><actividad nombre="Notificar al cliente (Sistema)" numeroVecesEjecutada="0" promedioTiempo="0"/><actividad nombre="Reabrir ticket (Cliente)" numeroVecesEjecutada="0" promedioTiempo="0"><arcoCon nombre="Cifrar ticket (Sistema)"/></actividad></actividades></helpDesk>